mcp_server_skill/__init__.py
mcp_server_skill/server.py
mcp_server_skill/skill_loader.py
mcp_server_skill/state.py
agentskill_mcp-0.1.3.dist-info/METADATA
agentskill_mcp-0.1.3.dist-info/WHEEL
agentskill_mcp-0.1.3.dist-info/entry_points.txt
agentskill_mcp-0.1.3.dist-info/licenses/LICENSE
agentskill_mcp-0.1.3.dist-info/RECORD
