Metadata-Version: 2.4
Name: agentskill-mcp
Version: 0.1.3
Summary: MCP server that enables any agent to use Claude Skills via progressive disclosure
Project-URL: Homepage, https://github.com/your-org/open-claudeskill
Project-URL: Repository, https://github.com/your-org/open-claudeskill
Project-URL: Documentation, https://github.com/your-org/open-claudeskill#readme
Author: Open-ClaudeSkill Contributors
License-File: LICENSE
Keywords: agent,ai,claude,mcp,skill
Classifier: Development Status :: 4 - Beta
Classifier: Intended Audience :: Developers
Classifier: License :: OSI Approved :: Apache Software License
Classifier: Programming Language :: Python :: 3
Classifier: Programming Language :: Python :: 3.10
Classifier: Programming Language :: Python :: 3.11
Classifier: Programming Language :: Python :: 3.12
Requires-Python: >=3.10
Requires-Dist: mcp>=1.0.0
Requires-Dist: pyyaml>=6.0.1
Requires-Dist: watchdog>=3.0.0
